rex_plus/__init__.py
rex_plus/__version__.py
rex_plus/core/__init__.py
rex_plus/core/search.py
rex_plus/core/sub.py
rex_plus-0.1.4.dist-info/LICENSE
rex_plus-0.1.4.dist-info/METADATA
rex_plus-0.1.4.dist-info/WHEEL
rex_plus-0.1.4.dist-info/top_level.txt
rex_plus-0.1.4.dist-info/RECORD
