Metadata-Version: 2.1
Name: rex-plus
Version: 0.1.4
Summary: You can match and replace strings with regular expressions.
Home-page: https://github.com/holbos-deng/rex_plus
Author: Holbos Deng
Author-email: 2292861292@qq.com
License: MIT
Platform: UNKNOWN
Classifier: License :: OSI Approved :: MIT License
Classifier: Programming Language :: Python
Classifier: Programming Language :: Python :: 3
Classifier: Programming Language :: Python :: 3.6
Classifier: Programming Language :: Python :: Implementation :: CPython
Classifier: Programming Language :: Python :: Implementation :: PyPy
Requires-Python: >=3.6.0
